summon/__init__.py
summon/__main__.py
summon/_plugin_spec.py
summon/_typer_app.py
summon/error.py
summon/execute.py
summon/plugins.py
summon/project.py
summon/py.typed
summon/tasks.py
summon_tasks-0.3.0.dist-info/LICENSE.md
summon_tasks-0.3.0.dist-info/METADATA
summon_tasks-0.3.0.dist-info/WHEEL
summon_tasks-0.3.0.dist-info/entry_points.txt
summon_tasks-0.3.0.dist-info/RECORD
