Metadata-Version: 2.1
Name: summon-tasks
Version: 0.3.0
Summary: 
License: MIT
Author: Tarcísio Eduardo Moreira Crocomo
Author-email: tarcisioe@pm.me
Requires-Python: >=3.8.1,<4.0.0
Classifier: License :: OSI Approved :: MIT License
Classifier: Programming Language :: Python :: 3
Classifier: Programming Language :: Python :: 3.9
Classifier: Programming Language :: Python :: 3.10
Classifier: Programming Language :: Python :: 3.11
Requires-Dist: pluggy (>=1.3.0,<2.0.0)
Requires-Dist: typer (>=0.9.0,<0.10.0)
Requires-Dist: typing-extensions (>=4.8.0,<5.0.0)
